kalshi_python/__init__.py
kalshi_python/api_client.py
kalshi_python/api_response.py
kalshi_python/configuration.py
kalshi_python/exceptions.py
kalshi_python/py.typed
kalshi_python/rest.py
kalshi_python/api/__init__.py
kalshi_python/api/api_keys_api.py
kalshi_python/api/communications_api.py
kalshi_python/api/events_api.py
kalshi_python/api/exchange_api.py
kalshi_python/api/markets_api.py
kalshi_python/api/milestones_api.py
kalshi_python/api/multivariate_collections_api.py
kalshi_python/api/portfolio_api.py
kalshi_python/api/series_api.py
kalshi_python/api/structured_targets_api.py
kalshi_python/models/__init__.py
kalshi_python/models/accept_quote_request.py
kalshi_python/models/amend_order_request.py
kalshi_python/models/amend_order_response.py
kalshi_python/models/announcement.py
kalshi_python/models/api_key.py
kalshi_python/models/batch_cancel_orders_request.py
kalshi_python/models/batch_cancel_orders_response.py
kalshi_python/models/batch_cancel_orders_response_responses_inner.py
kalshi_python/models/batch_create_orders_request.py
kalshi_python/models/batch_create_orders_response.py
kalshi_python/models/batch_create_orders_response_responses_inner.py
kalshi_python/models/cancel_order_response.py
kalshi_python/models/candlestick.py
kalshi_python/models/create_api_key_request.py
kalshi_python/models/create_api_key_response.py
kalshi_python/models/create_order_group_request.py
kalshi_python/models/create_order_group_response.py
kalshi_python/models/create_order_request.py
kalshi_python/models/create_order_response.py
kalshi_python/models/create_quote_request.py
kalshi_python/models/create_quote_response.py
kalshi_python/models/create_rfq_request.py
kalshi_python/models/create_rfq_response.py
kalshi_python/models/daily_schedule.py
kalshi_python/models/decrease_order_request.py
kalshi_python/models/decrease_order_response.py
kalshi_python/models/error_response.py
kalshi_python/models/error_response_error.py
kalshi_python/models/event.py
kalshi_python-2.1.3.dist-info/METADATA
kalshi_python-2.1.3.dist-info/WHEEL
kalshi_python-2.1.3.dist-info/top_level.txt
kalshi_python-2.1.3.dist-info/RECORD
