Metadata-Version: 2.4
Name: kalshi-python
Version: 2.1.3
Summary: Kalshi Trading API
Home-page: https://github.com/Kalshi/exchange-infra
Author: Kalshi Support
Author-email: Kalshi Support <support@kalshi.com>
License-Expression: LicenseRef-Proprietary
Project-URL: Repository, https://github.com/GIT_USER_ID/GIT_REPO_ID
Keywords: OpenAPI,OpenAPI-Generator,Kalshi Trading API
Requires-Python: >=3.9
Requires-Dist: urllib3<3.0.0,>=2.1.0
Requires-Dist: python-dateutil>=2.8.2
Requires-Dist: pydantic>=2
Requires-Dist: typing-extensions>=4.7.1
Requires-Dist: lazy-imports<2,>=1
Dynamic: author
Dynamic: home-page
